LICENSE
MANIFEST.in
README.md
pyproject.toml
setup.py
fate/__init__.py
fate/__init__.py.bak
fate/animation.py
fate/effects.py
fate/interactive.py
fate/shortcuts.py
fate/styles.py
fate/utils.py
fate/__pycache__/__init__.cpython-311.pyc
fate/__pycache__/animation.cpython-311.pyc
fate/__pycache__/effects.cpython-311.pyc
fate/__pycache__/interactive.cpython-311.pyc
fate/__pycache__/styles.cpython-311.pyc
fate/__pycache__/utils.cpython-311.pyc
fated.egg-info/PKG-INFO
fated.egg-info/SOURCES.txt
fated.egg-info/dependency_links.txt
fated.egg-info/requires.txt
fated.egg-info/top_level.txt