Metadata-Version: 2.4
Name: fated
Version: 0.3.0
Summary: A Python library for adding visual effects to terminal text output
Author-email: Fred <fredised@users.noreply.github.com>
Project-URL: Homepage, https://github.com/fredised/fated
Project-URL: Bug Tracker, https://github.com/fredised/fated/issues
Classifier: Programming Language :: Python :: 3
Classifier: License :: OSI Approved :: MIT License
Classifier: Operating System :: OS Independent
Classifier: Topic :: Software Development :: Libraries :: Python Modules
Classifier: Topic :: Text Processing :: General
Classifier: Intended Audience :: Developers
Requires-Python: >=3.7
License-File: LICENSE
Requires-Dist: build>=1.1.1
Requires-Dist: setuptools>=68.0.0
Requires-Dist: twine>=4.0.2
Dynamic: license-file
